chibi_xl_deploy/__init__.py
chibi_xl_deploy/cli.py
chibi_xl_deploy/config.py
chibi_xl_deploy/urls.py
chibi_xl_deploy-0.0.2.dist-info/AUTHORS.rst
chibi_xl_deploy-0.0.2.dist-info/LICENSE
chibi_xl_deploy-0.0.2.dist-info/METADATA
chibi_xl_deploy-0.0.2.dist-info/WHEEL
chibi_xl_deploy-0.0.2.dist-info/entry_points.txt
chibi_xl_deploy-0.0.2.dist-info/top_level.txt
chibi_xl_deploy-0.0.2.dist-info/RECORD
