Metadata-Version: 2.1
Name: chibi-xl-deploy
Version: 0.0.2
Summary: lib for use the XL Deploy api
Home-page: https://github.com/dem4ply/chibi_xl_deploy
Author: dem4ply
Author-email: dem4ply@gmail.com
License: WTFPL
Keywords: chibi_xl_deploy
Platform: UNKNOWN
Classifier: Development Status :: 2 - Pre-Alpha
Classifier: Intended Audience :: Developers
Classifier: License :: Public Domain
Classifier: Natural Language :: English
Classifier: Programming Language :: Python :: 3.7
Classifier: Programming Language :: Python :: 3.8
Requires-Dist: chibi-requests (>=0.6.1)
